djangorestsearch-0.15.0.dist-info/licenses/LICENSE
rest_search/__init__.py
rest_search/decorators.py
rest_search/forms.py
rest_search/indexers.py
rest_search/middleware.py
rest_search/schemas.py
rest_search/tasks.py
rest_search/views.py
djangorestsearch-0.15.0.dist-info/METADATA
djangorestsearch-0.15.0.dist-info/WHEEL
djangorestsearch-0.15.0.dist-info/top_level.txt
djangorestsearch-0.15.0.dist-info/RECORD
