Metadata-Version: 2.4
Name: djangorestsearch
Version: 0.15.0
Summary: OpenSearch integration for Django
Author-email: Jeremy Lainé <jeremy.laine@m4x.org>
License-Expression: BSD-2-Clause
Project-URL: Homepage, https://github.com/wemap/django-rest-search
Project-URL: Documentation, https://django-rest-search.readthedocs.io/
Classifier: Development Status :: 5 - Production/Stable
Classifier: Intended Audience :: Developers
Classifier: Operating System :: OS Independent
Classifier: Programming Language :: Python
Classifier: Programming Language :: Python :: 3
Classifier: Programming Language :: Python :: 3.9
Classifier: Programming Language :: Python :: 3.10
Classifier: Programming Language :: Python :: 3.11
Classifier: Programming Language :: Python :: 3.12
Classifier: Programming Language :: Python :: 3.13
Requires-Python: >=3.9
License-File: LICENSE
Requires-Dist: aws-requests-auth>=0.3.0
Requires-Dist: botocore
Requires-Dist: opensearch-py<3.0.0,>=2.0.0
Provides-Extra: dev
Requires-Dist: celery; extra == "dev"
Requires-Dist: coverage[toml]>=7.2.2; extra == "dev"
Requires-Dist: django; extra == "dev"
Requires-Dist: djangorestframework; extra == "dev"
Requires-Dist: inflection; extra == "dev"
Requires-Dist: ruff; extra == "dev"
Requires-Dist: uritemplate; extra == "dev"
Dynamic: license-file
